xarray_schema/__init__.py
xarray_schema/base.py
xarray_schema/components.py
xarray_schema/dataarray.py
xarray_schema/dataset.py
xarray_schema/types.py
xarray_schema-0.0.3.dist-info/LICENSE
xarray_schema-0.0.3.dist-info/METADATA
xarray_schema-0.0.3.dist-info/WHEEL
xarray_schema-0.0.3.dist-info/top_level.txt
xarray_schema-0.0.3.dist-info/RECORD
