Metadata-Version: 2.1
Name: xarray-schema
Version: 0.0.3
Summary: Schema validation for Xarray objects
Home-page: https://github.com/carbonplan/xarray-schema
Maintainer: Joe Hamman
Maintainer-email: joe@carbonplan.org
License: MIT
Keywords: xarray,schema
Platform: UNKNOWN
Classifier: Development Status :: 3 - Alpha
Classifier: License :: OSI Approved :: MIT License
Classifier: Operating System :: OS Independent
Classifier: Intended Audience :: Science/Research
Classifier: Programming Language :: Python
Classifier: Programming Language :: Python :: 3
Classifier: Programming Language :: Python :: 3.8
Classifier: Programming Language :: Python :: 3.9
Classifier: Topic :: Scientific/Engineering
Requires-Python: >=3.8
License-File: LICENSE
